[
{"tahun":"2000","jenis":"padi","hasil":"20"}, 
{"tahun":"2001","jenis":"padi","hasil":"40"}, 
{"tahun":"2002","jenis":"padi","hasil":"60"}, 
{"tahun":"2003","jenis":"padi","hasil":"50"}, 
{"tahun":"2004","jenis":"padi","hasil":"30"}, 
{"tahun":"2005","jenis":"padi","hasil":"40"}, 
{"tahun":"2006","jenis":"padi","hasil":"40"}, 
{"tahun":"2007","jenis":"padi","hasil":"50"}, 
{"tahun":"2000","jenis":"jagung","hasil":"30"},
{"tahun":"2001","jenis":"jagung","hasil":"40"}, 
{"tahun":"2002","jenis":"jagung","hasil":"40"}, 
{"tahun":"2003","jenis":"jagung","hasil":"50"},
{"tahun":"2004","jenis":"jagung","hasil":"20"}, 
{"tahun":"2005","jenis":"jagung","hasil":"40"}, 
{"tahun":"2006","jenis":"jagung","hasil":"60"}, 
{"tahun":"2007","jenis":"jagung","hasil":"50"}
]